pytest_collect_formatter2/__init__.py
pytest_collect_formatter2/plugin.py
pytest_collect_formatter2-0.1.3.dist-info/AUTHORS.rst
pytest_collect_formatter2-0.1.3.dist-info/LICENSE
pytest_collect_formatter2-0.1.3.dist-info/METADATA
pytest_collect_formatter2-0.1.3.dist-info/WHEEL
pytest_collect_formatter2-0.1.3.dist-info/entry_points.txt
pytest_collect_formatter2-0.1.3.dist-info/top_level.txt
pytest_collect_formatter2-0.1.3.dist-info/RECORD
