Metadata-Version: 2.1
Name: pytest-collect-formatter2
Version: 0.1.3
Summary: Formatter for pytest collect output
Home-page: https://github.com/15klli/pytest-collect-formatter2
Author: lingo
Author-email: likanglin@bytedance.com
License: MIT license
Project-URL: Bug Tracker, https://github.com/15klli/pytest-collect-formatter2
Keywords: pytest,py.test,yaml,json
Platform: UNKNOWN
Classifier: Framework :: Pytest
Classifier: Development Status :: 5 - Production/Stable
Classifier: Intended Audience :: Developers
Classifier: License :: OSI Approved :: MIT License
Classifier: Natural Language :: English
Classifier: Programming Language :: Python :: 3.6
Classifier: Programming Language :: Python :: 3.7
Classifier: Programming Language :: Python :: 3.8
Requires-Python: >=3.6
Requires-Dist: dicttoxml
Requires-Dist: PyYAML
